README.txt
buildanddistribute.sh
setup.cfg
setup.py
docs/HISTORY.txt
ely/__init__.py
ely.kupu_useragent_patch.egg-info/PKG-INFO
ely.kupu_useragent_patch.egg-info/SOURCES.txt
ely.kupu_useragent_patch.egg-info/dependency_links.txt
ely.kupu_useragent_patch.egg-info/entry_points.txt
ely.kupu_useragent_patch.egg-info/namespace_packages.txt
ely.kupu_useragent_patch.egg-info/not-zip-safe
ely.kupu_useragent_patch.egg-info/requires.txt
ely.kupu_useragent_patch.egg-info/top_level.txt
ely/kupu_useragent_patch/__init__.py
ely/kupu_useragent_patch/configure.zcml
ely/kupu_useragent_patch/patches.py