Metadata-Version: 1.0
Name: ely.kupu-useragent-patch
Version: 1.2
Summary: remove user agent test from the test for isKupuEnabled
Home-page: UNKNOWN
Author: Matt Halstead
Author-email: matt@elyt.com
License: GPL
Keywords: plone kupu
Platform: UNKNOWN
Classifier: Programming Language :: Python
Classifier: Topic :: Software Development :: Libraries :: Python Modules
